[
  {
    "signature": "async ContentObjects({\n  \"libraryId\": \"ilibCrdtQy812xpjcsA4WG2cTj5eZtq\"\n});",
    "result": "[\n  {\n    \"id\": \"iq__DT2asWi7i7zt1xvBdSgwFtggijK\",\n    \"versions\": [\n      {\n        \"id\": \"iq__DT2asWi7i7zt1xvBdSgwFtggijK\",\n        \"hash\": \"hq__4rqEEHdW97bm9QgMevCqpbrNPRJCW8qPX1oAcDeTxpW5gcDVVhdV65MZd5NkaFNnaoLTPv2PE1\",\n        \"type\": \"hq__E5ekWcPN97eEucCnDrx6eBE1APi94yv5TVBve64MEbehWpPdM62fhYhkv3L5WwAsrXdZ1bWv3Z\",\n        \"meta\": {\n          \"toMerge\": {\n            \"merge\": \"me\",\n            \"new\": \"metadata\"\n          },\n          \"toReplace\": {\n            \"new\": \"metadata\"\n          }\n        }\n      },\n      {\n        \"id\": \"iq__DT2asWi7i7zt1xvBdSgwFtggijK\",\n        \"hash\": \"hq__EnXLEHDQhtvWVFNzQyazZqu9zxYxt11PrTS8sasVBFsckk4ATZumM7ukGea8iJGfpQB7kdGBys\",\n        \"type\": \"hq__E5ekWcPN97eEucCnDrx6eBE1APi94yv5TVBve64MEbehWpPdM62fhYhkv3L5WwAsrXdZ1bWv3Z\",\n        \"meta\": {\n          \"toDelete\": {\n            \"delete\": \"me\"\n          },\n          \"toMerge\": {\n            \"merge\": \"me\"\n          },\n          \"toReplace\": {\n            \"replace\": \"me\"\n          }\n        }\n      }\n    ]\n  }\n]"
  }
]