[
  {
    "signature": "async DownloadPart({\n  \"libraryId\": \"ilib22zDKQk2uSQkgkdsAYsLYsRUFLYL\",\n  \"objectId\": \"iq__rntQJ8cH7KbKuG1D6D8d91vGHgm\",\n  \"partHash\": \"hqp_QmVAo3wNeEhjeMMcCPSG3LYXEZMdkyj77UwPf2HcPckVfD\",\n  \"format\": \"arrayBuffer\"\n});",
    "result": "<ArrayBuffer 100000>"
  },
  {
    "signature": "async DownloadPart({\n  \"libraryId\": \"ilib22zDKQk2uSQkgkdsAYsLYsRUFLYL\",\n  \"objectId\": \"iq__rntQJ8cH7KbKuG1D6D8d91vGHgm\",\n  \"partHash\": \"hqp_QmauXvPyR98oTqopixiwMUHXGgGzwZHM7GECwsFzCsn3jX\",\n  \"format\": \"arrayBuffer\"\n});",
    "result": "<ArrayBuffer 100000>"
  }
]