[
  {
    "signature": "async UploadFiles({\n  \"libraryId\": \"ilib3wpbycgg5PWTYAiTaZQG24LqL2xL\",\n  \"objectId\": \"iq__3wpbycgg5PWTYAiTaZQG24LqL2xL\",\n  \"writeToken\": \"tqw_8fWNsfTqQMZsVgzJKkM7fKKmebA7Ukhqy\",\n  \"data\": \"<ArrayBuffer 101254>\",\n  \"encrypted\": false,\n  \"fileInfo\": [\n    {\n      \"path\": \"display_image\",\n      \"mime_type\": \"image/*\",\n      \"size\": 101254,\n      \"type\": \"file\"\n    }\n  ]\n});"
  },
  {
    "signature": "async UploadFiles({\n  \"libraryId\": \"ilib3wpbycgg5PWTYAiTaZQG24LqL2xL\",\n  \"objectId\": \"iq__3WDfMNH5BGayTAGj9GijcwiAJdGx\",\n  \"writeToken\": \"tqw_Lqz6jrfEWyJwU9cAF9M779EWtzJsh6f2u\",\n  \"fileInfo\": [\n    {\n      \"path\": \"testDirectory/File 1\",\n      \"type\": \"file\",\n      \"mime_type\": \"text/plain\",\n      \"size\": 100000\n    },\n    {\n      \"path\": \"testDirectory/File 2\",\n      \"type\": \"file\",\n      \"mime_type\": \"text/plain\",\n      \"size\": 100000\n    }\n  ],\n  \"callback\": \"<function>\"\n});"
  },
  {
    "signature": "async UploadFiles({\n  \"libraryId\": \"ilib3ssRA4rhPP9noEyVqwTykvGLgAPk\",\n  \"objectId\": \"iq__kEtfnzPjvxrLPKWiVFq3vroSKf1\",\n  \"writeToken\": \"tqw_ByfEdL6Hgigd23TefiqtxZsCBdTvC3ZE2\",\n  \"fileInfo\": [\n    {\n      \"path\": \"Video.mp4\",\n      \"mime_type\": \"video/mp4\",\n      \"size\": 3738907,\n      \"type\": \"file\"\n    }\n  ],\n  \"encryption\": \"none\"\n});"
  }
]