[
  {
    "signature": "async Visibility({\n  \"id\": \"iq__26LhSe9vNhqqjHv6ghtNwyzG6pp3\"\n});",
    "result": "100"
  },
  {
    "signature": "async Visibility({\n  \"id\": \"iq__4Kq3bCuaesopTzoyUUgtEWBmn5if\"\n});",
    "result": "10"
  },
  {
    "signature": "async Visibility({\n  \"id\": \"iq__2zqa4gZ8N3DH1QWakR2e5UowDLF1\"\n});",
    "result": "10"
  },
  {
    "signature": "async Visibility({\n  \"id\": \"iq__42gJKSsPoLCNkmEiDopEfPSujc2e\"\n});",
    "result": "10"
  },
  {
    "signature": "async Visibility({\n  \"id\": \"iq__HuhHukBBkqZaVC9TWsSutKU4G19\"\n});",
    "result": "10"
  },
  {
    "signature": "async Visibility({\n  \"id\": \"iq__2qXmASFyWJDAEnxw2nTZw4r6hDDM\"\n});",
    "result": "10"
  },
  {
    "signature": "async Visibility({\n  \"id\": \"iq__31MnG9224pFjY6rirwrkwGAtmbta\"\n});",
    "result": "10"
  },
  {
    "signature": "async Visibility({\n  \"id\": \"iq__26NEcQJCYJ1mQxdCdXuge9bHBwGm\"\n});",
    "result": "10"
  }
]