[
  {
    "signature": " MakeClonable({\n  \"string\": \"value\",\n  \"number\": 0.5,\n  \"nested\": {\n    \"value\": \"something\"\n  },\n  \"set\": \"<Set>\",\n  \"map\": \"<Map>\",\n  \"arrayBuffer\": \"<ArrayBuffer 20>\",\n  \"blob\": \"<Blob>\"\n});",
    "result": "{\n  \"string\": \"value\",\n  \"number\": 0.5,\n  \"nested\": {\n    \"value\": \"something\"\n  },\n  \"set\": \"<Set>\",\n  \"map\": \"<Map>\",\n  \"arrayBuffer\": \"<ArrayBuffer 20>\",\n  \"blob\": \"<Blob>\"\n}"
  },
  {
    "signature": " MakeClonable(\"value\");",
    "result": "\"value\""
  },
  {
    "signature": " MakeClonable(0.5);",
    "result": "0.5"
  },
  {
    "signature": " MakeClonable({\n  \"value\": \"something\"\n});",
    "result": "{\n  \"value\": \"something\"\n}"
  },
  {
    "signature": " MakeClonable(2);",
    "result": "2"
  },
  {
    "signature": " MakeClonable(\"b\");",
    "result": "\"b\""
  },
  {
    "signature": " MakeClonable({\n  \"a\": \"b\"\n});",
    "result": "{\n  \"a\": \"b\"\n}"
  },
  {
    "signature": " MakeClonable();"
  },
  {
    "signature": " MakeClonable({});",
    "result": "<Map>"
  },
  {
    "signature": " MakeClonable({});",
    "result": "<Set>"
  },
  {
    "signature": " MakeClonable({\n  \"0\": 101,\n  \"1\": 102,\n  \"2\": 102,\n  \"3\": 53,\n  \"4\": 53,\n  \"5\": 100,\n  \"6\": 98,\n  \"7\": 49,\n  \"8\": 50,\n  \"9\": 50,\n  \"10\": 97,\n  \"11\": 99,\n  \"12\": 98,\n  \"13\": 51,\n  \"14\": 98,\n  \"15\": 55,\n  \"16\": 53,\n  \"17\": 56,\n  \"18\": 99,\n  \"19\": 54,\n  \"20\": 52,\n  \"21\": 50,\n  \"22\": 98,\n  \"23\": 48,\n  \"24\": 56,\n  \"25\": 97,\n  \"26\": 102,\n  \"27\": 53,\n  \"28\": 56,\n  \"29\": 57,\n  \"30\": 48,\n  \"31\": 100,\n  \"32\": 49,\n  \"33\": 49,\n  \"34\": 53,\n  \"35\": 97,\n  \"36\": 53,\n  \"37\": 54,\n  \"38\": 99,\n  \"39\": 55\n});",
    "result": "<ArrayBuffer 40>"
  },
  {
    "signature": " MakeClonable({});",
    "result": "<ArrayBuffer 20>"
  },
  {
    "signature": " MakeClonable({});",
    "result": "<Blob>"
  },
  {
    "signature": " MakeClonable({\n  \"size\": 0,\n  \"timeout\": 0\n});"
  },
  {
    "signature": " MakeClonable();"
  },
  {
    "signature": " MakeClonable({});",
    "result": "\"Error\""
  },
  {
    "signature": " MakeClonable({\n  \"string\": \"value\",\n  \"number\": 0.5,\n  \"nested\": {\n    \"value\": \"something\"\n  },\n  \"map\": \"<Map>\",\n  \"set\": \"<Set>\",\n  \"buffer\": \"<Buffer 40>\",\n  \"arrayBuffer\": \"<ArrayBuffer 20>\",\n  \"blob\": \"<Blob>\",\n  \"response\": \"<Response 0>\",\n  \"error\": {}\n});",
    "result": "{\n  \"string\": \"value\",\n  \"number\": 0.5,\n  \"nested\": {\n    \"value\": \"something\"\n  },\n  \"map\": \"<Map>\",\n  \"set\": \"<Set>\",\n  \"buffer\": \"<ArrayBuffer 40>\",\n  \"arrayBuffer\": \"<ArrayBuffer 20>\",\n  \"blob\": \"<Blob>\",\n  \"error\": \"Error\"\n}"
  }
]